geofast/__init__.py
geofast/cache.py
geofast/cli.py
geofast/core.py
geofast/cuda_kernels.py
geofast/executor.py
geofast/formats.py
geofast/geo_ops.py
geofast/parallel.py
geofast/primitives.py
geofast/spatial_index.py
geofast/utils.py
geofast-0.2.1.dist-info/licenses/LICENSE
geofast-0.2.1.dist-info/METADATA
geofast-0.2.1.dist-info/WHEEL
geofast-0.2.1.dist-info/entry_points.txt
geofast-0.2.1.dist-info/top_level.txt
geofast-0.2.1.dist-info/RECORD
