Metadata-Version: 2.4
Name: geofast
Version: 0.2.1
Summary: High-performance geospatial processing with GPU acceleration, Numba JIT, and format conversion
Author-email: Norm <norm@headingshelicopters.com>
License: MIT
Keywords: geospatial,gis,gpu,cuda,numba,parallel,shapely,geopandas,kml,geojson,gpx,mpz,format-conversion
Classifier: Development Status :: 4 - Beta
Classifier: Intended Audience :: Developers
Classifier: Intended Audience :: Science/Research
Classifier: License :: OSI Approved :: MIT License
Classifier: Operating System :: OS Independent
Classifier: Programming Language :: Python :: 3
Classifier: Programming Language :: Python :: 3.9
Classifier: Programming Language :: Python :: 3.10
Classifier: Programming Language :: Python :: 3.11
Classifier: Programming Language :: Python :: 3.12
Classifier: Topic :: Scientific/Engineering :: GIS
Classifier: Topic :: Scientific/Engineering :: Information Analysis
Requires-Python: >=3.9
License-File: LICENSE
Requires-Dist: numpy>=1.21
Provides-Extra: geo
Requires-Dist: geopandas>=0.12; extra == "geo"
Requires-Dist: shapely>=2.0; extra == "geo"
Requires-Dist: fiona>=1.8; extra == "geo"
Requires-Dist: pyproj>=3.0; extra == "geo"
Provides-Extra: gpu
Requires-Dist: cupy-cuda12x; extra == "gpu"
Provides-Extra: numba
Requires-Dist: numba>=0.56; extra == "numba"
Provides-Extra: full
Requires-Dist: numba>=0.56; extra == "full"
Requires-Dist: shapely>=2.0; extra == "full"
Provides-Extra: all
Requires-Dist: geofast[geo,numba]; extra == "all"
Provides-Extra: dev
Requires-Dist: pytest>=7.0; extra == "dev"
Requires-Dist: pytest-cov; extra == "dev"
Requires-Dist: black; extra == "dev"
Requires-Dist: ruff; extra == "dev"
Dynamic: license-file
